{
	"info": {
		"_postman_id": "e2ef01be-0a6f-4610-9f17-183ce642d714",
		"name": "My Cars API",
		"schema": "https://schema.getpostman.com/json/collection/v2.1.0/collection.json",
		"_exporter_id": "30236019"
	},
	"item": [
		{
			"name": "CRUD",
			"item": [
				{
					"name": "Get all cars",
					"request": {
						"method": "GET",
						"header": [],
						"url": {
							"raw": "{{baseUrl}}/cars/",
							"host": [
								"{{baseUrl}}"
							],
							"path": [
								"cars",
								""
							]
						}
					},
					"response": []
				},
				{
					"name": "Get single car",
					"request": {
						"method": "GET",
						"header": [],
						"url": {
							"raw": "{{baseUrl}}/cars/1",
							"host": [
								"{{baseUrl}}"
							],
							"path": [
								"cars",
								"1"
							]
						}
					},
					"response": []
				},
				{
					"name": "Add car",
					"request": {
						"method": "POST",
						"header": [],
						"body": {
							"mode": "raw",
							"raw": "{\r\n    \"manufacturer\": \"BMW\",\r\n    \"model\": \"A beg Paul Biya Mouf dey\",\r\n    \"build\": \"2025\"\r\n}"
						},
						"url": {
							"raw": "{{baseUrl}}/cars",
							"host": [
								"{{baseUrl}}"
							],
							"path": [
								"cars"
							]
						}
					},
					"response": []
				}
			]
		},
		{
			"name": "Health",
			"item": [
				{
					"name": "Health",
					"request": {
						"method": "GET",
						"header": [],
						"url": {
							"raw": "{{baseUrl}}/api/health",
							"host": [
								"{{baseUrl}}"
							],
							"path": [
								"api",
								"health"
							]
						}
					},
					"response": []
				}
			]
		}
	],
	"variable": [
		{
			"key": "baseUrl",
			"value": "http://localhost:5000"
		}
	]
}